DataMemory/DataMemory.sv
`timescale 1ns/1ps
module Data_Memory#(Bits = 64, MemSize = 16)(
  input clk,
  input [Bits-1:0] mem_access_addr,// dirección de acceso, Compartido por read and write port
  input [Bits-1:0] mem_write_data,// Puerto de escritura
  input mem_write_en, 
  input mem_read,
  output [Bits-1:0] mem_read_data);// Puerto de lectura
  reg [Bits - 1:0] memory [MemSize - 1:0]; //Arreglo de memoria para cargar la ram
  wire [Bits-1:0] ram_addr = mem_access_addr[Bits-1:0]; 
  initial
  begin
    $readmemb("Data.mem", memory); //Lectura de memoria
  end
  always @(posedge clk) begin
    if (mem_write_en)
      memory[ram_addr] <= mem_write_data;
  end
  assign mem_read_data = (mem_read==1'b1) ? memory[ram_addr]:16'd0;
endmodule

DataMemory/DataMemory_tb.sv
`include "DataMemory.sv"
`timescale 1ns/1ps
module Data_Memory_tb #(Bits=64, MemSize=16);

  reg clk;
  reg [Bits-1:0] mem_access_addr;// dirección de acceso, Compartido por read and write port
  reg [Bits-1:0] mem_write_data;// Puerto de escritura
  reg mem_write_en;
  reg mem_read;
  reg [Bits-1:0] mem_read_data;// Puerto de lectura
  Data_Memory #(.Bits(Bits), .MemSize(MemSize)) dut ( .clk(clk), .mem_access_addr(mem_access_addr), .mem_write_data(mem_write_data), .mem_write_en(mem_write_en), .mem_read(mem_read), .mem_read_data(mem_read_data));
  always begin
        #5 clk = ~clk;
  end
  initial 
    begin
      clk <= 0;
      mem_access_addr = 64'd0;
      mem_write_en = 1'b0;
      mem_write_data = 64'd0;
      $dumpfile("DataMemory.vcd");
      $dumpvars(5,dut);
    //Revisamos la información de las posiciones de memoria 1, 2 y 3
      mem_read = 1'b1;
      mem_access_addr = 64'd1;
      #10
      mem_access_addr = 64'd2;
      #10
      mem_access_addr = 64'd3;
      #10
      mem_read = 1'b0;
      #10
    //Guardamos información en la posicion de memoria 1
      mem_write_en = 1'b1;
      #10
      mem_access_addr = 64'd1;
      mem_write_data = 64'hfa5b9;
      #10
      mem_write_en = 1'b0;
      #10
    //Accesamos a la información de la posición de memoria
      mem_read = 1'b1;
      mem_access_addr = 64'd1;
      mem_read = 1'b0;
      #10
    //Se repite el proceso sin habilitar la lectura ni la escirtura
      mem_read = 1'b0;
      mem_access_addr = 64'd1;
      #10
      mem_write_data = 64'd256;
      mem_access_addr = 64'd5;
      #10
    //Hacemos lectura del registro 1  para corrobar la información que se
    //guardó
      mem_read = 1'b1;
      mem_access_addr = 64'd1;
      #10
      mem_read = 1'b0;
      #10
      $finish;
   end 
endmodule

DataMemory/DataMemory.vcd
$date
	Thu Apr 11 13:47:35 2024
$end

$version
	Synopsys VCS version R-2020.12-SP2_Full64
$end

$timescale
	1ps
$end

$comment Csum: 1 f09641781620c8cb $end


$scope module Data_Memory_tb $end

$scope module dut $end
$var wire 1 ! clk $end
$var wire 64 " mem_access_addr [63:0] $end
$var wire 64 # mem_write_data [63:0] $end
$var wire 1 $ mem_write_en $end
$var wire 1 % mem_read $end
$var wire 64 & mem_read_data [63:0] $end
$var wire 64 ' ram_addr [63:0] $end
$upscope $end

$upscope $end

$enddefinitions $end

#0
$dumpvars
b0000000000000000000000000000000000000000000000000000000000000001 '
0!
b0000000000000000000000000000000000000000000000000000000000000001 "
b0000000000000000000000000000000000000000000000000000000000000000 #
0$
1%
b0000000000000000000000000000000000000000000000100000000000000001 &
$end
#5000
1!
#10000
b0000000000000000000000000000000000000000000000000000000000000010 "
b0000000000000000000000000000000000000000000000000000000000000010 '
0!
b0000000000000000000000000000000000000000000000010000000000000001 &
#15000
1!
#20000
b0000000000000000000000000000000000000000000000000000000000000011 "
b0000000000000000000000000000000000000000000000000000000000000011 '
0!
b0000000000000000000000000000000000000000000000100000000000000001 &
#25000
1!
#30000
0%
0!
b0000000000000000000000000000000000000000000000000000000000000000 &
#35000
1!
#40000
1$
0!
#45000
1!
#50000
b0000000000000000000000000000000000000000000000000000000000000001 "
b0000000000000000000000000000000000000000000000000000000000000001 '
b0000000000000000000000000000000000000000000011111010010110111001 #
0!
#55000
1!
#60000
0$
0!
#65000
1!
#70000
0!
#75000
1!
#80000
0!
#85000
1!
#90000
b0000000000000000000000000000000000000000000000000000000100000000 #
b0000000000000000000000000000000000000000000000000000000000000101 "
b0000000000000000000000000000000000000000000000000000000000000101 '
0!
#95000
1!
#100000
1%
b0000000000000000000000000000000000000000000000000000000000000001 "
b0000000000000000000000000000000000000000000000000000000000000001 '
0!
b0000000000000000000000000000000000000000000011111010010110111001 &
#105000
1!
#110000
0%
0!
b0000000000000000000000000000000000000000000000000000000000000000 &
