BancoRegistros/RegistroFFD.sv
module RegistroFFD #(parameter Bits = 64)(data, clk, rst, enable, q);
  input [Bits-1:0] data;
  input clk, rst, enable;
  output reg [Bits-1:0] q;
  always @(posedge clk or posedge rst) begin
    if (rst) begin
      q <=  0; 
    end 
    else if (enable) begin
      q <= data;
    end
    else begin
      q <= q;
    end
  end   
endmodule

BancoRegistros/Onehot.sv
`timescale 1ns/1ps
module Onehot #(parameter N = 32) 
  (
  input [$clog2(N)-1:0] Selector,
  output Outn [N-1:0]
  );
  genvar i;
  generate
    for(i=0; i < N; i = i + 1) begin
	localparam localsel = i;
	assign Outn[i] = (localsel == Selector) ? 1:0;
    end
  endgenerate
endmodule

Procesador_RISCV/MuxParam.sv
`include "Onehot.sv"
`timescale 1ns/1ps
module MuxParam #(parameter N, Bits) 
(
  input [$clog2(N)-1:0] read_code,
  input [Bits-1:0] D [N-1:0],
  output [Bits-1:0] Q 
);

  wire Enable [N-1:0];
  Onehot #(.N(N)) Decodificador (.Outn(Enable), .Selector(read_code));
  genvar i;
  generate
    for(i=0; i < N; i = i + 1) begin: Bit_
      assign Q = (Enable[i]==1) ? D[i] : {Bits{1'bz}};
    end
  endgenerate
endmodule

BancoRegistros/hotbit.sv
`timescale 1ns/1ps
module hotbit#(parameter N = 32) (
  input [$clog2(N)-1:0] reg_wr_cod,
  input wr_en,
  output reg Outn [N-1:0]
  );
  genvar i;
  generate
    for(i=0; i < N; i = i + 1) begin
      localparam localsel = i;
      assign Outn[i] = (localsel == reg_wr_cod && wr_en == 1) ? 1:0;
     end
  endgenerate
endmodule

BancoRegistros/BancoRegistros.sv
`include "MuxParam.sv"
`include "hotbit.sv"
`include "RegistroFFD.sv"
module BancoRegistros #(parameter N = 32, Bits = 64) 
  ( 
  input [$clog2(N)-1:0] ptr_rd_1, ptr_rd_2, ptr_wr, //Puntero de rs1, rs2 y rd respectivamente
  input [Bits-1:0] data_wr, //Info para rd
  input wr_en, //Habilitador de escritura
  input rst, clk,
  output reg [Bits-1:0] data_rd_1, data_rd_2 //Info de rs1 y rs2
);  
  wire Enable [N-1:0];
  wire [Bits-1:0] D_out [N-1:0] ;
  hotbit #(.N(N)) Habilitador_escritura (.wr_en(wr_en), .reg_wr_cod(ptr_wr), .Outn(Enable));
  genvar i;
  generate
    for(i=0; i < N; i = i + 1) begin: Registro_
      RegistroFFD #(.Bits(Bits))(.data(data_wr), .enable(Enable[i]) , .clk(clk) ,.rst(rst), .q(D_out[i]));
    end
  endgenerate
  MuxParam #(.N(N), .Bits(Bits)) Mux_rd_1(.read_code(ptr_rd_1), .D(D_out), .Q(data_rd_1));
  MuxParam #(.N(N), .Bits(Bits)) Mux_rd_2(.read_code(ptr_rd_2), .D(D_out), .Q(data_rd_2));
  endmodule

BancoRegistros/BancoRegistros_tb.sv
`include "BancoRegistros.sv"
`timescale 1ns/1ps
module BancoRegistros_tb #(parameter N = 32, Bits=64);
  reg [$clog2(N)-1:0] ptr_rd_1; //Puntero rs1
  reg [$clog2(N)-1:0] ptr_rd_2; //Puntero rs2
  reg [$clog2(N)-1:0] ptr_wr; //Puntero de rd
  reg [Bits-1:0] data_wr;  //Info para rd
  reg wr_en; //Habilitador de escritura
  reg rst, clk;
  wire [Bits-1:0] data_rd_1;
  wire [Bits-1:0] data_rd_2;
  BancoRegistros #(.N(N), .Bits(Bits)) DUT (.ptr_rd_1(ptr_rd_1), .ptr_rd_2(ptr_rd_2), .ptr_wr(ptr_wr), .data_wr(data_wr), .wr_en(wr_en), .rst(rst), .clk(clk), .data_rd_1(data_rd_1), .data_rd_2(data_rd_2));
  always #10 clk=~clk;
  initial begin
    wr_en = 1'b0;
    ptr_wr = 5'd0;
    data_wr = 64'd0;
    ptr_rd_1 = 5'd0;
    ptr_rd_2 = 5'd0;
    $dumpfile ("BancoRegistros.vcd");
    $dumpvars (5,DUT);
    clk = 0;
    rst = 1;
    #20;
    rst = 0;
    wr_en = 1'b1;
    #20;
    ptr_wr = 5'd1;
    data_wr = 64'd10;
    #20
    ptr_wr = 5'd2;
    data_wr = 64'd20;
    #20
    ptr_wr = 5'd3;
    data_wr = 64'd30;
    #20
    ptr_wr = 5'd4;
    data_wr = 64'd40;
    #20
    ptr_wr = 5'd5;
    data_wr = 64'd50;
    #20
    ptr_wr = 5'd6;
    data_wr = 64'd60;
    #20
    ptr_rd_1 = 5'd1;
    ptr_rd_2 = 5'd2;
    #20
    ptr_rd_1 = 5'd3;
    ptr_rd_2 = 5'd4;
    wr_en = 1'b0;
    data_wr = 64'd1;
    ptr_wr = 5'd1;
    #20;
    data_wr = 64'd2;
    ptr_wr = 5'd2;
    #20;
    ptr_rd_1 = 5'd5;
    ptr_rd_2 = 5'd6;
    data_wr = 64'd3;
    ptr_wr = 5'd3;
    #20;
    data_wr = 64'd4;
    ptr_wr = 5'd4;
    #20;
    ptr_rd_1 = 5'd1;
    ptr_rd_2 = 5'd2;
    #40
    $finish;
  end
endmodule

BancoRegistros/BancoRegistros.vcd
$date
	Mon Apr  1 15:22:40 2024
$end

$version
	Synopsys VCS version R-2020.12-SP2_Full64
$end

$timescale
	1ps
$end

$comment Csum: 1 a37add3b5b97d981 $end


$scope module BancoRegistros_tb $end

$scope module DUT $end
$var wire 5 ! ptr_rd_1 [4:0] $end
$var wire 5 " ptr_rd_2 [4:0] $end
$var wire 5 # ptr_wr [4:0] $end
$var wire 64 $ data_wr [63:0] $end
$var wire 1 % wr_en $end
$var wire 1 & rst $end
$var wire 1 ' clk $end
$var reg 64 ( data_rd_1 [63:0] $end
$var reg 64 ) data_rd_2 [63:0] $end

$scope module Habilitador_escritura $end
$var wire 5 # reg_wr_cod [4:0] $end
$var wire 1 % wr_en $end
$upscope $end


$scope module Mux_rd_1 $end
$var wire 5 ! read_code [4:0] $end
$var wire 64 * Q [63:0] $end

$scope module Decodificador $end
$var wire 5 ! Selector [4:0] $end
$upscope $end

$upscope $end


$scope module Mux_rd_2 $end
$var wire 5 " read_code [4:0] $end
$var wire 64 + Q [63:0] $end

$scope module Decodificador $end
$var wire 5 " Selector [4:0] $end
$upscope $end

$upscope $end


$scope module Registro_[0].RegistroFFD $end
$var wire 64 $ data [63:0] $end
$var wire 1 ' clk $end
$var wire 1 & rst $end
$var wire 1 , enable $end
$var reg 64 - q [63:0] $end
$upscope $end


$scope module Registro_[1].RegistroFFD $end
$var wire 64 $ data [63:0] $end
$var wire 1 ' clk $end
$var wire 1 & rst $end
$var wire 1 . enable $end
$var reg 64 / q [63:0] $end
$upscope $end


$scope module Registro_[2].RegistroFFD $end
$var wire 64 $ data [63:0] $end
$var wire 1 ' clk $end
$var wire 1 & rst $end
$var wire 1 0 enable $end
$var reg 64 1 q [63:0] $end
$upscope $end


$scope module Registro_[3].RegistroFFD $end
$var wire 64 $ data [63:0] $end
$var wire 1 ' clk $end
$var wire 1 & rst $end
$var wire 1 2 enable $end
$var reg 64 3 q [63:0] $end
$upscope $end


$scope module Registro_[4].RegistroFFD $end
$var wire 64 $ data [63:0] $end
$var wire 1 ' clk $end
$var wire 1 & rst $end
$var wire 1 4 enable $end
$var reg 64 5 q [63:0] $end
$upscope $end


$scope module Registro_[5].RegistroFFD $end
$var wire 64 $ data [63:0] $end
$var wire 1 ' clk $end
$var wire 1 & rst $end
$var wire 1 6 enable $end
$var reg 64 7 q [63:0] $end
$upscope $end


$scope module Registro_[6].RegistroFFD $end
$var wire 64 $ data [63:0] $end
$var wire 1 ' clk $end
$var wire 1 & rst $end
$var wire 1 8 enable $end
$var reg 64 9 q [63:0] $end
$upscope $end


$scope module Registro_[7].RegistroFFD $end
$var wire 64 $ data [63:0] $end
$var wire 1 ' clk $end
$var wire 1 & rst $end
$var wire 1 : enable $end
$var reg 64 ; q [63:0] $end
$upscope $end


$scope module Registro_[8].RegistroFFD $end
$var wire 64 $ data [63:0] $end
$var wire 1 ' clk $end
$var wire 1 & rst $end
$var wire 1 < enable $end
$var reg 64 = q [63:0] $end
$upscope $end


$scope module Registro_[9].RegistroFFD $end
$var wire 64 $ data [63:0] $end
$var wire 1 ' clk $end
$var wire 1 & rst $end
$var wire 1 > enable $end
$var reg 64 ? q [63:0] $end
$upscope $end


$scope module Registro_[10].RegistroFFD $end
$var wire 64 $ data [63:0] $end
$var wire 1 ' clk $end
$var wire 1 & rst $end
$var wire 1 @ enable $end
$var reg 64 A q [63:0] $end
$upscope $end


$scope module Registro_[11].RegistroFFD $end
$var wire 64 $ data [63:0] $end
$var wire 1 ' clk $end
$var wire 1 & rst $end
$var wire 1 B enable $end
$var reg 64 C q [63:0] $end
$upscope $end


$scope module Registro_[12].RegistroFFD $end
$var wire 64 $ data [63:0] $end
$var wire 1 ' clk $end
$var wire 1 & rst $end
$var wire 1 D enable $end
$var reg 64 E q [63:0] $end
$upscope $end


$scope module Registro_[13].RegistroFFD $end
$var wire 64 $ data [63:0] $end
$var wire 1 ' clk $end
$var wire 1 & rst $end
$var wire 1 F enable $end
$var reg 64 G q [63:0] $end
$upscope $end


$scope module Registro_[14].RegistroFFD $end
$var wire 64 $ data [63:0] $end
$var wire 1 ' clk $end
$var wire 1 & rst $end
$var wire 1 H enable $end
$var reg 64 I q [63:0] $end
$upscope $end


$scope module Registro_[15].RegistroFFD $end
$var wire 64 $ data [63:0] $end
$var wire 1 ' clk $end
$var wire 1 & rst $end
$var wire 1 J enable $end
$var reg 64 K q [63:0] $end
$upscope $end


$scope module Registro_[16].RegistroFFD $end
$var wire 64 $ data [63:0] $end
$var wire 1 ' clk $end
$var wire 1 & rst $end
$var wire 1 L enable $end
$var reg 64 M q [63:0] $end
$upscope $end


$scope module Registro_[17].RegistroFFD $end
$var wire 64 $ data [63:0] $end
$var wire 1 ' clk $end
$var wire 1 & rst $end
$var wire 1 N enable $end
$var reg 64 O q [63:0] $end
$upscope $end


$scope module Registro_[18].RegistroFFD $end
$var wire 64 $ data [63:0] $end
$var wire 1 ' clk $end
$var wire 1 & rst $end
$var wire 1 P enable $end
$var reg 64 Q q [63:0] $end
$upscope $end


$scope module Registro_[19].RegistroFFD $end
$var wire 64 $ data [63:0] $end
$var wire 1 ' clk $end
$var wire 1 & rst $end
$var wire 1 R enable $end
$var reg 64 S q [63:0] $end
$upscope $end


$scope module Registro_[20].RegistroFFD $end
$var wire 64 $ data [63:0] $end
$var wire 1 ' clk $end
$var wire 1 & rst $end
$var wire 1 T enable $end
$var reg 64 U q [63:0] $end
$upscope $end


$scope module Registro_[21].RegistroFFD $end
$var wire 64 $ data [63:0] $end
$var wire 1 ' clk $end
$var wire 1 & rst $end
$var wire 1 V enable $end
$var reg 64 W q [63:0] $end
$upscope $end


$scope module Registro_[22].RegistroFFD $end
$var wire 64 $ data [63:0] $end
$var wire 1 ' clk $end
$var wire 1 & rst $end
$var wire 1 X enable $end
$var reg 64 Y q [63:0] $end
$upscope $end


$scope module Registro_[23].RegistroFFD $end
$var wire 64 $ data [63:0] $end
$var wire 1 ' clk $end
$var wire 1 & rst $end
$var wire 1 Z enable $end
$var reg 64 [ q [63:0] $end
$upscope $end


$scope module Registro_[24].RegistroFFD $end
$var wire 64 $ data [63:0] $end
$var wire 1 ' clk $end
$var wire 1 & rst $end
$var wire 1 \ enable $end
$var reg 64 ] q [63:0] $end
$upscope $end


$scope module Registro_[25].RegistroFFD $end
$var wire 64 $ data [63:0] $end
$var wire 1 ' clk $end
$var wire 1 & rst $end
$var wire 1 ^ enable $end
$var reg 64 _ q [63:0] $end
$upscope $end


$scope module Registro_[26].RegistroFFD $end
$var wire 64 $ data [63:0] $end
$var wire 1 ' clk $end
$var wire 1 & rst $end
$var wire 1 ` enable $end
$var reg 64 a q [63:0] $end
$upscope $end


$scope module Registro_[27].RegistroFFD $end
$var wire 64 $ data [63:0] $end
$var wire 1 ' clk $end
$var wire 1 & rst $end
$var wire 1 b enable $end
$var reg 64 c q [63:0] $end
$upscope $end


$scope module Registro_[28].RegistroFFD $end
$var wire 64 $ data [63:0] $end
$var wire 1 ' clk $end
$var wire 1 & rst $end
$var wire 1 d enable $end
$var reg 64 e q [63:0] $end
$upscope $end


$scope module Registro_[29].RegistroFFD $end
$var wire 64 $ data [63:0] $end
$var wire 1 ' clk $end
$var wire 1 & rst $end
$var wire 1 f enable $end
$var reg 64 g q [63:0] $end
$upscope $end


$scope module Registro_[30].RegistroFFD $end
$var wire 64 $ data [63:0] $end
$var wire 1 ' clk $end
$var wire 1 & rst $end
$var wire 1 h enable $end
$var reg 64 i q [63:0] $end
$upscope $end


$scope module Registro_[31].RegistroFFD $end
$var wire 64 $ data [63:0] $end
$var wire 1 ' clk $end
$var wire 1 & rst $end
$var wire 1 j enable $end
$var reg 64 k q [63:0] $end
$upscope $end

$upscope $end

$upscope $end

$enddefinitions $end

#0
$dumpvars
b0000000000000000000000000000000000000000000000000000000000000000 A
b0000000000000000000000000000000000000000000000000000000000000000 C
b0000000000000000000000000000000000000000000000000000000000000000 E
b0000000000000000000000000000000000000000000000000000000000000000 G
b0000000000000000000000000000000000000000000000000000000000000000 I
b0000000000000000000000000000000000000000000000000000000000000000 K
b0000000000000000000000000000000000000000000000000000000000000000 M
b0000000000000000000000000000000000000000000000000000000000000000 O
b0000000000000000000000000000000000000000000000000000000000000000 Q
b0000000000000000000000000000000000000000000000000000000000000000 S
b0000000000000000000000000000000000000000000000000000000000000000 /
b0000000000000000000000000000000000000000000000000000000000000000 U
b0000000000000000000000000000000000000000000000000000000000000000 W
b0000000000000000000000000000000000000000000000000000000000000000 Y
b0000000000000000000000000000000000000000000000000000000000000000 [
b0000000000000000000000000000000000000000000000000000000000000000 ]
b0000000000000000000000000000000000000000000000000000000000000000 _
b0000000000000000000000000000000000000000000000000000000000000000 a
b0000000000000000000000000000000000000000000000000000000000000000 c
b0000000000000000000000000000000000000000000000000000000000000000 e
b0000000000000000000000000000000000000000000000000000000000000000 g
b0000000000000000000000000000000000000000000000000000000000000000 1
b0000000000000000000000000000000000000000000000000000000000000000 i
b0000000000000000000000000000000000000000000000000000000000000000 k
b0000000000000000000000000000000000000000000000000000000000000000 3
b0000000000000000000000000000000000000000000000000000000000000000 5
b0000000000000000000000000000000000000000000000000000000000000000 7
b0000000000000000000000000000000000000000000000000000000000000000 9
b0000000000000000000000000000000000000000000000000000000000000000 ;
b0000000000000000000000000000000000000000000000000000000000000000 =
b0000000000000000000000000000000000000000000000000000000000000000 ?
b0000000000000000000000000000000000000000000000000000000000000000 (
b0000000000000000000000000000000000000000000000000000000000000000 )
b0000000000000000000000000000000000000000000000000000000000000000 -
b00000 !
b00000 "
b00000 #
b0000000000000000000000000000000000000000000000000000000000000000 $
0%
1&
0'
b0000000000000000000000000000000000000000000000000000000000000000 *
b0000000000000000000000000000000000000000000000000000000000000000 +
0,
0.
00
02
04
06
08
0:
0<
0>
0@
0B
0D
0F
0H
0J
0L
0N
0P
0R
0T
0V
0X
0Z
0\
0^
0`
0b
0d
0f
0h
0j
$end
#10000
1'
#20000
0&
1%
0'
1,
#30000
1'
#40000
b00001 #
b0000000000000000000000000000000000000000000000000000000000001010 $
0'
1.
0,
#50000
1'
b0000000000000000000000000000000000000000000000000000000000001010 /
#60000
b00010 #
b0000000000000000000000000000000000000000000000000000000000010100 $
0'
10
0.
#70000
1'
b0000000000000000000000000000000000000000000000000000000000010100 1
#80000
b00011 #
b0000000000000000000000000000000000000000000000000000000000011110 $
0'
12
00
#90000
1'
b0000000000000000000000000000000000000000000000000000000000011110 3
#100000
b00100 #
b0000000000000000000000000000000000000000000000000000000000101000 $
0'
14
02
#110000
1'
b0000000000000000000000000000000000000000000000000000000000101000 5
#120000
b00101 #
b0000000000000000000000000000000000000000000000000000000000110010 $
0'
16
04
#130000
1'
b0000000000000000000000000000000000000000000000000000000000110010 7
#140000
b00110 #
b0000000000000000000000000000000000000000000000000000000000111100 $
0'
18
06
#150000
1'
b0000000000000000000000000000000000000000000000000000000000111100 9
#160000
b00001 !
b00010 "
0'
b0000000000000000000000000000000000000000000000000000000000001010 *
b0000000000000000000000000000000000000000000000000000000000001010 (
b0000000000000000000000000000000000000000000000000000000000010100 +
b0000000000000000000000000000000000000000000000000000000000010100 )
#170000
1'
#180000
b00011 !
b00100 "
0%
b0000000000000000000000000000000000000000000000000000000000000001 $
b00001 #
0'
08
b0000000000000000000000000000000000000000000000000000000000011110 *
b0000000000000000000000000000000000000000000000000000000000011110 (
b0000000000000000000000000000000000000000000000000000000000101000 +
b0000000000000000000000000000000000000000000000000000000000101000 )
#190000
1'
#200000
b0000000000000000000000000000000000000000000000000000000000000010 $
b00010 #
0'
#210000
1'
#220000
b00101 !
b00110 "
b0000000000000000000000000000000000000000000000000000000000000011 $
b00011 #
0'
b0000000000000000000000000000000000000000000000000000000000110010 *
b0000000000000000000000000000000000000000000000000000000000110010 (
b0000000000000000000000000000000000000000000000000000000000111100 +
b0000000000000000000000000000000000000000000000000000000000111100 )
#230000
1'
#240000
b0000000000000000000000000000000000000000000000000000000000000100 $
b00100 #
0'
#250000
1'
#260000
b00001 !
b00010 "
0'
b0000000000000000000000000000000000000000000000000000000000001010 *
b0000000000000000000000000000000000000000000000000000000000001010 (
b0000000000000000000000000000000000000000000000000000000000010100 +
b0000000000000000000000000000000000000000000000000000000000010100 )
